antareslauncher/__init__.py
antareslauncher/advanced_launch.py
antareslauncher/antares_launcher.py
antareslauncher/basic_launch.py
antareslauncher/config.py
antareslauncher/exceptions.py
antareslauncher/logger_initializer.py
antareslauncher/main.py
antareslauncher/main_option_parser.py
antareslauncher/parameters_reader.py
antareslauncher/study_dto.py
antareslauncher/data_repo/__init__.py
antareslauncher/data_repo/data_repo_tinydb.py
antareslauncher/data_repo/data_reporter.py
antareslauncher/display/__init__.py
antareslauncher/display/display_terminal.py
antareslauncher/remote_environnement/__init__.py
antareslauncher/remote_environnement/remote_environment_with_slurm.py
antareslauncher/remote_environnement/slurm_script_features.py
antareslauncher/remote_environnement/ssh_connection.py
antareslauncher/use_cases/__init__.py
antareslauncher/use_cases/check_remote_queue/__init__.py
antareslauncher/use_cases/check_remote_queue/check_queue_controller.py
antareslauncher/use_cases/check_remote_queue/slurm_queue_show.py
antareslauncher/use_cases/create_list/__init__.py
antareslauncher/use_cases/create_list/study_list_composer.py
antareslauncher/use_cases/kill_job/__init__.py
antareslauncher/use_cases/kill_job/job_kill_controller.py
antareslauncher/use_cases/launch/__init__.py
antareslauncher/use_cases/launch/launch_controller.py
antareslauncher/use_cases/launch/study_submitter.py
antareslauncher/use_cases/launch/study_zip_uploader.py
antareslauncher/use_cases/retrieve/__init__.py
antareslauncher/use_cases/retrieve/clean_remote_server.py
antareslauncher/use_cases/retrieve/download_final_zip.py
antareslauncher/use_cases/retrieve/final_zip_extractor.py
antareslauncher/use_cases/retrieve/log_downloader.py
antareslauncher/use_cases/retrieve/retrieve_controller.py
antareslauncher/use_cases/retrieve/state_updater.py
antareslauncher/use_cases/retrieve/study_retriever.py
antareslauncher/use_cases/wait_loop_controller/__init__.py
antares_launcher-1.4.6.dist-info/LICENSE
antares_launcher-1.4.6.dist-info/METADATA
antares_launcher-1.4.6.dist-info/WHEEL
antares_launcher-1.4.6.dist-info/entry_points.txt
antares_launcher-1.4.6.dist-info/top_level.txt
antares_launcher-1.4.6.dist-info/RECORD
