Metadata-Version: 2.1
Name: Antares_Launcher
Version: 1.4.6
Summary: Antares_Launcher to run Antares on a remote linux machine
Home-page: https://github.com/AntaresSimulatorTeam/antares-launcher.git
Author: RTE, Antares Web Team
Author-email: andrea.sgattoni@rte-france.com
License: Apache Software License
Platform: linux-x86_64
Platform: macosx-10.14-x86_64
Platform: macosx-10.15-x86_64
Platform: macosx-11-x86_64
Platform: macosx-12-x86_64
Platform: macosx-13-x86_64
Platform: win-amd64
Classifier: Development Status :: 5 - Production/Stable
Classifier: Programming Language :: Python :: 3 :: Only
Classifier: Programming Language :: Python :: 3.8
Classifier: Programming Language :: Python :: 3.9
Classifier: Programming Language :: Python :: 3.10
Classifier: Programming Language :: Python :: 3.11
Classifier: Environment :: Console
Classifier: License :: OSI Approved :: Apache Software License
Classifier: Natural Language :: English
Classifier: Operating System :: Microsoft :: Windows
Classifier: Operating System :: POSIX :: Linux
Classifier: Operating System :: MacOS :: MacOS X
Requires-Python: >=3.8, <4
License-File: LICENSE
Requires-Dist: paramiko ~=3.4.1
Requires-Dist: PyYAML
Requires-Dist: tinydb <4.8
Requires-Dist: tqdm <4.65
Requires-Dist: bcrypt >=5.0.0
Provides-Extra: dev
Requires-Dist: black ; extra == 'dev'
Requires-Dist: check-manifest ; extra == 'dev'
Requires-Dist: isort ; extra == 'dev'
Requires-Dist: mypy ; extra == 'dev'
Provides-Extra: docs
Requires-Dist: m2r ; extra == 'docs'
Requires-Dist: recommonmark ; extra == 'docs'
Requires-Dist: sphinx ; extra == 'docs'
Requires-Dist: sphinx-rtd-theme ; extra == 'docs'
Requires-Dist: docutils <0.19 ; extra == 'docs'
Provides-Extra: pyinstaller
Requires-Dist: pyinstaller ~=5.8.0 ; extra == 'pyinstaller'
Provides-Extra: test
Requires-Dist: pytest ~=7.2.1 ; extra == 'test'
Requires-Dist: pytest-cov ~=4.0.0 ; extra == 'test'
Requires-Dist: pytest-xdist ~=3.1.0 ; extra == 'test'
